prarabdha/__init__.py
prarabdha/cli.py
prarabdha/commands/__init__.py
prarabdha/commands/deploy.py
prarabdha/commands/start.py
prarabdha/commands/stop.py
prarabdha/scaffolders/__init__.py
prarabdha/scaffolders/enhanced_python_scaffolder.py
prarabdha/scaffolders/generic_scaffolder.py
prarabdha/scaffolders/java_scaffolder.py
prarabdha/scaffolders/nodejs_scaffolder.py
prarabdha/scaffolders/python_scaffolder.py
prarabdha/utils/__init__.py
prarabdha/utils/helpers.py
prarabdha_ai-1.4.0.dist-info/METADATA
prarabdha_ai-1.4.0.dist-info/WHEEL
prarabdha_ai-1.4.0.dist-info/entry_points.txt
prarabdha_ai-1.4.0.dist-info/top_level.txt
prarabdha_ai-1.4.0.dist-info/RECORD
