Metadata-Version: 2.4
Name: prarabdha-ai
Version: 1.4.0
Summary: A CLI tool for scaffolding backend services with interactive menus
Home-page: https://github.com/prarabdha/prarabdha-ai
Author: Prarabdha
Author-email: prarabdha@example.com
Classifier: Development Status :: 4 - Beta
Classifier: Intended Audience :: Developers
Classifier: License :: OSI Approved :: MIT License
Classifier: Operating System :: OS Independent
Classifier: Programming Language :: Python :: 3
Classifier: Programming Language :: Python :: 3.8
Classifier: Programming Language :: Python :: 3.9
Classifier: Programming Language :: Python :: 3.10
Classifier: Programming Language :: Python :: 3.11
Requires-Python: >=3.8
Requires-Dist: click>=8.0.0
Requires-Dist: rich>=12.0.0
Requires-Dist: inquirer>=3.0.0
Requires-Dist: pyyaml>=6.0
Requires-Dist: psutil>=5.9.0
Dynamic: author
Dynamic: author-email
Dynamic: classifier
Dynamic: description
Dynamic: description-content-type
Dynamic: home-page
Dynamic: requires-dist
Dynamic: requires-python
Dynamic: summary
